_pylibdatachannel.cpython-313-x86_64-linux-gnu.so
pylibdatachannel/__init__.py
pylibdatachannel/__init__.pyi
pylibdatachannel/py.typed
pylibdatachannel.libs/libcrypto-bdaed0ea.so.1.1.1k
pylibdatachannel.libs/libdatachannel-ad68f30b.so.0.22.2
pylibdatachannel.libs/libssl-60250281.so.1.1.1k
pylibdatachannel-0.2.0.dist-info/METADATA
pylibdatachannel-0.2.0.dist-info/WHEEL
pylibdatachannel-0.2.0.dist-info/top_level.txt
pylibdatachannel-0.2.0.dist-info/RECORD
pylibdatachannel-0.2.0.dist-info/licenses/LICENSE
