Metadata-Version: 2.4
Name: pylibdatachannel
Version: 0.2.0
Summary: Wrapper around libdatachannel
Author-email: Ondřej Novák <git@npost.cz>
License: MIT License
Project-URL: Homepage, https://github.com/handycz/pylibdatachannel
Keywords: libdatachannel,webrtc
Classifier: Development Status :: 3 - Alpha
Classifier: Intended Audience :: Developers
Classifier: Operating System :: POSIX
Classifier: Programming Language :: Python :: Implementation :: CPython
Classifier: Programming Language :: Python
Classifier: Topic :: Internet
Classifier: Topic :: Software Development :: Libraries
Classifier: Topic :: Software Development
Requires-Python: >=3.11
License-File: LICENSE
Provides-Extra: test
Requires-Dist: attrs==24.2.0; extra == "test"
Requires-Dist: filelock==3.16.1; extra == "test"
Requires-Dist: iniconfig==2.0.0; extra == "test"
Requires-Dist: mypy==1.13.0; extra == "test"
Requires-Dist: mypy-extensions==1.0.0; extra == "test"
Requires-Dist: packaging==24.2; extra == "test"
Requires-Dist: pluggy==1.5.0; extra == "test"
Requires-Dist: pybind11==2.13.6; extra == "test"
Requires-Dist: pytest==8.3.3; extra == "test"
Requires-Dist: pytest-asyncio==0.24.0; extra == "test"
Requires-Dist: pytest-mypy==0.10.3; extra == "test"
Requires-Dist: pytest-ruff==0.4.1; extra == "test"
Requires-Dist: pytest-timeout==2.3.1; extra == "test"
Requires-Dist: ruff==0.8.1; extra == "test"
Requires-Dist: types-setuptools==75.6.0.20241126; extra == "test"
Requires-Dist: typing-extensions==4.12.2; extra == "test"
Dynamic: license-file
